ultima_scraper_collection/__init__.py
ultima_scraper_collection/config.py
ultima_scraper_collection/helpers/__init__.py
ultima_scraper_collection/helpers/main_helper.py
ultima_scraper_collection/managers/__init__.py
ultima_scraper_collection/managers/content_manager.py
ultima_scraper_collection/managers/database_manager/__init__.py
ultima_scraper_collection/managers/database_manager/connections/__init__.py
ultima_scraper_collection/managers/database_manager/connections/sqlite/__init__.py
ultima_scraper_collection/managers/database_manager/connections/sqlite/databases/user_data/migration/__init__.py
ultima_scraper_collection/managers/database_manager/connections/sqlite/databases/user_data/migration/alembic/README
ultima_scraper_collection/managers/database_manager/connections/sqlite/databases/user_data/migration/alembic/env.py
ultima_scraper_collection/managers/database_manager/connections/sqlite/databases/user_data/migration/alembic/script.py.mako
ultima_scraper_collection/managers/database_manager/connections/sqlite/databases/user_data/migration/alembic/versions/0d4d92c0498e_content.py
ultima_scraper_collection/managers/database_manager/connections/sqlite/databases/user_data/migration/alembic/versions/1454e4d1c6b8_content.py
ultima_scraper_collection/managers/database_manager/connections/sqlite/databases/user_data/migration/alembic/versions/37c4f2719d65_content.py
ultima_scraper_collection/managers/database_manager/connections/sqlite/databases/user_data/migration/alembic/versions/5493253cc03c_content.py
ultima_scraper_collection/managers/database_manager/connections/sqlite/databases/user_data/migration/alembic/versions/b791cf213df9_content.py
ultima_scraper_collection/managers/database_manager/connections/sqlite/databases/user_data/migration/alembic/versions/d2f2002f3c36_content.py
ultima_scraper_collection/managers/database_manager/connections/sqlite/databases/user_data/migration/alembic.ini
ultima_scraper_collection-2.3.34.dist-info/METADATA
ultima_scraper_collection-2.3.34.dist-info/WHEEL
ultima_scraper_collection-2.3.34.dist-info/RECORD
