Metadata-Version: 2.3
Name: ultima-scraper-collection
Version: 2.3.34
Summary: 
Author: UltimaHoarder
Author-email: 1285176+UltimaHoarder@users.noreply.github.com
Requires-Python: >=3.10,<4
Classifier: Programming Language :: Python :: 3
Classifier: Programming Language :: Python :: 3.10
Classifier: Programming Language :: Python :: 3.11
Classifier: Programming Language :: Python :: 3.12
Classifier: Programming Language :: Python :: 3.13
Requires-Dist: alembic (>=1.9.2,<2.0.0)
Requires-Dist: alive-progress (>=3.1.5,<4.0.0)
Requires-Dist: appdirs (>=1.4.4,<2.0.0)
Requires-Dist: ffmpeg-python (>=0.2.0,<0.3.0)
Requires-Dist: inflection (>=0.5.1,<0.6.0)
Requires-Dist: netifaces (>=0.11.0,<0.12.0)
Requires-Dist: psycopg2 (>=2.9.5,<3.0.0)
Requires-Dist: pydantic (>=2.0,<3.0)
Requires-Dist: redis (>=6.4.0,<7.0.0)
Requires-Dist: rich (>=14.0.0,<15.0.0)
Requires-Dist: sqlalchemy (>=2.0.1,<3.0.0)
Requires-Dist: sshtunnel (>=0.4.0,<0.5.0)
Requires-Dist: ujson (>=5.10.0,<6.0.0)
Requires-Dist: ultima-scraper-api (>=2.0,<3.0)
Requires-Dist: ultima-scraper-db (>=0.4,<0.5)
Requires-Dist: ultima-scraper-detector (>=0.1,<0.2)
Requires-Dist: ultima-scraper-renamer (>=1.0,<2.0)
